{
    "version":"2023.12.18",
    "region":"KR",
    "lists":{
        "ServerZoneIpcType":[
            {
                "name":"PlayerSpawn",
                "opcode":513
            },
            {
                "name":"NpcSpawn",
                "opcode":143
            },
            {
                "name":"NpcSpawn2",
                "opcode":151
            },
            {
                "name":"ActorFreeSpawn",
                "opcode":101
            },
            {
                "name":"ObjectSpawn",
                "opcode":567
            },
            {
                "name":"ObjectDespawn",
                "opcode":310
            },
            {
                "name":"CreateTreasure",
                "opcode":897
            },
            {
                "name":"OpenTreasure",
                "opcode":662
            },
            {
                "name":"TreasureFadeOut",
                "opcode":535
            },
            {
                "name":"ActorMove",
                "opcode":649
            },
            {
                "name":"_record_unk10_",
                "opcode":183
            },
            {
                "name":"Transfer",
                "opcode":833
            },
            {
                "name":"Effect",
                "opcode":459
            },
            {
                "name":"AoeEffect8",
                "opcode":602
            },
            {
                "name":"AoeEffect16",
                "opcode":949
            },
            {
                "name":"AoeEffect24",
                "opcode":142
            },
            {
                "name":"AoeEffect32",
                "opcode":964
            },
            {
                "name":"ActorCast",
                "opcode":415
            },
            {
                "name":"ActorControl",
                "opcode":224
            },
            {
                "name":"ActorControlTarget",
                "opcode":534
            },
            {
                "name":"ActorControlSelf",
                "opcode":103
            },
            {
                "name":"DirectorVars",
                "opcode":237
            },
            {
                "name":"ContentDirectorSync",
                "opcode":892
            },
            {
                "name":"_record_unk23_",
                "opcode":104
            },
            {
                "name":"EnvironmentControl",
                "opcode":978
            },
            {
                "name":"_record_unk29_",
                "opcode":699
            },
            {
                "name":"LandSetMap",
                "opcode":648
            },
            {
                "name":"_record_unk31_",
                "opcode":498
            },
            {
                "name":"EventStart",
                "opcode":230
            },
            {
                "name":"EventFinish",
                "opcode":281
            },
            {
                "name":"EventPlay",
                "opcode":972
            },
            {
                "name":"EventPlay4",
                "opcode":600
            },
            {
                "name":"EventPlay8",
                "opcode":348
            },
            {
                "name":"EventPlay16",
                "opcode":463
            },
            {
                "name":"EventPlay32",
                "opcode":753
            },
            {
                "name":"EventPlay64",
                "opcode":405
            },
            {
                "name":"EventPlay128",
                "opcode":689
            },
            {
                "name":"EventPlay255",
                "opcode":165
            },
            {
                "name":"BattleTalk2",
                "opcode":245
            },
            {
                "name":"BattleTalk4",
                "opcode":454
            },
            {
                "name":"BattleTalk8",
                "opcode":697
            },
            {
                "name":"BalloonTalk2",
                "opcode":381
            },
            {
                "name":"BalloonTalk4",
                "opcode":253
            },
            {
                "name":"BalloonTalk8",
                "opcode":218
            },
            {
                "name":"SystemLogMessage",
                "opcode":502
            },
            {
                "name":"SystemLogMessage32",
                "opcode":896
            },
            {
                "name":"SystemLogMessage48",
                "opcode":831
            },
            {
                "name":"SystemLogMessage80",
                "opcode":138
            },
            {
                "name":"SystemLogMessage144",
                "opcode":884
            },
            {
                "name":"NpcYell",
                "opcode":625
            },
            {
                "name":"ActorSetPos",
                "opcode":188
            },
            {
                "name":"PrepareZoning",
                "opcode":341
            },
            {
                "name":"_record_unk58_",
                "opcode":733
            },
            {
                "name":"WeatherChange",
                "opcode":445
            },
            {
                "name":"UpdateParty",
                "opcode":891
            },
            {
                "name":"UpdateAlliance",
                "opcode":707
            },
            {
                "name":"UpdateSpAlliance",
                "opcode":668
            },
            {
                "name":"UpdateHpMpTp",
                "opcode":680
            },
            {
                "name":"StatusEffectList",
                "opcode":134
            },
            {
                "name":"StatusEffectList2",
                "opcode":627
            },
            {
                "name":"StatusEffectList3",
                "opcode":619
            },
            {
                "name":"EurekaStatusEffectList",
                "opcode":876
            },
            {
                "name":"BossStatusEffectList",
                "opcode":136
            },
            {
                "name":"EffectResult",
                "opcode":160
            },
            {
                "name":"EffectResult4",
                "opcode":960
            },
            {
                "name":"EffectResult8",
                "opcode":612
            },
            {
                "name":"EffectResult16",
                "opcode":590
            },
            {
                "name":"EffectResultBasic",
                "opcode":553
            },
            {
                "name":"EffectResultBasic4",
                "opcode":331
            },
            {
                "name":"EffectResultBasic8",
                "opcode":629
            },
            {
                "name":"EffectResultBasic16",
                "opcode":585
            },
            {
                "name":"EffectResultBasic32",
                "opcode":681
            },
            {
                "name":"EffectResultBasic64",
                "opcode":512
            },
            {
                "name":"PartyPos",
                "opcode":416
            },
            {
                "name":"AlliancePos",
                "opcode":724
            },
            {
                "name":"SpAlliancePos",
                "opcode":965
            },
            {
                "name":"PlaceMarker",
                "opcode":657
            },
            {
                "name":"PlaceFieldMarkerPreset",
                "opcode":468
            },
            {
                "name":"PlaceFieldMarker",
                "opcode":618
            },
            {
                "name":"ActorGauge",
                "opcode":958
            },
            {
                "name":"CharaVisualEffect",
                "opcode":832
            },
            {
                "name":"Fall",
                "opcode":676
            },
            {
                "name":"UpdateHate",
                "opcode":543
            },
            {
                "name":"UpdateHater",
                "opcode":735
            },
            {
                "name":"FirstAttack",
                "opcode":433
            },
            {
                "name":"ModelEquip",
                "opcode":157
            },
            {
                "name":"EquipDisplayFlags",
                "opcode":163
            },
            {
                "name":"UnMount",
                "opcode":140
            },
            {
                "name":"Mount",
                "opcode":515
            },
            {
                "name":"PlayMotionSync",
                "opcode":787
            },
            {
                "name":"CountdownInitiate",
                "opcode":378
            },
            {
                "name":"CountdownCancel",
                "opcode":864
            },
            {
                "name":"InitZone",
                "opcode":441
            },
            {
                "name":"Examine",
                "opcode":736
            },
            {
                "name":"ExamineSearchInfo",
                "opcode":475
            },
            {
                "name":"InventoryActionAck",
                "opcode":338
            },
            {
                "name":"MarketBoardItemListing",
                "opcode":588
            },
            {
                "name":"MarketBoardItemListingCount",
                "opcode":212
            },
            {
                "name":"MarketBoardItemListingHistory",
                "opcode":161
            },
            {
                "name":"MarketBoardSearchResult",
                "opcode":919
            },
            {
                "name":"MarketBoardPurchase",
                "opcode":940
            },
            {
                "name":"PlayerSetup",
                "opcode":252
            },
            {
                "name":"PlayerStats",
                "opcode":589
            },
            {
                "name":"Playtime",
                "opcode":146
            },
            {
                "name":"UpdateClassInfo",
                "opcode":222
            },
            {
                "name":"UpdateInventorySlot",
                "opcode":285
            },
            {
                "name":"UpdateSearchInfo",
                "opcode":748
            },
            {
                "name":"WardLandInfo",
                "opcode":985
            },
            {
                "name":"CEDirector",
                "opcode":540
            },
            {
                "name":"Logout",
                "opcode":691
            },
            {
                "name":"FreeCompanyInfo",
                "opcode":123
            },
            {
                "name":"FreeCompanyDialog",
                "opcode":863
            },
            {
                "name":"AirshipStatusList",
                "opcode":113
            },
            {
                "name":"AirshipStatus",
                "opcode":499
            },
            {
                "name":"AirshipExplorationResult",
                "opcode":858
            },
            {
                "name":"SubmarineStatusList",
                "opcode":982
            },
            {
                "name":"SubmarineProgressionStatus",
                "opcode":292
            },
            {
                "name":"SubmarineExplorationResult",
                "opcode":530
            },
            {
                "name":"CFPreferredRole",
                "opcode":994
            },
            {
                "name":"CompanyAirshipStatus",
                "opcode":159
            },
            {
                "name":"CompanySubmersibleStatus",
                "opcode":756
            },
            {
                "name":"ContentFinderNotifyPop",
                "opcode":483
            },
            {
                "name":"FateInfo",
                "opcode":712
            },
            {
                "name":"UpdateRecastTimes",
                "opcode":968
            },
            {
                "name":"SocialList",
                "opcode":434
            },
            {
                "name":"IslandWorkshopSupplyDemand",
                "opcode":166
            },
            {
                "name":"RSV",
                "opcode":168
            },
            {
                "name":"RSF",
                "opcode":120
            }
        ],
        "ClientZoneIpcType":[
            {
                "name":"ActionRequest",
                "opcode":957
            },
            {
                "name":"ActionRequestGroundTargeted",
                "opcode":269
            },
            {
                "name":"ChatHandler",
                "opcode":522
            },
            {
                "name":"ClientTrigger",
                "opcode":796
            },
            {
                "name":"InventoryModifyHandler",
                "opcode":954
            },
            {
                "name":"MarketBoardPurchaseHandler",
                "opcode":239
            },
            {
                "name":"SetSearchInfoHandler",
                "opcode":375
            },
            {
                "name":"UpdatePositionHandler",
                "opcode":581
            },
            {
                "name":"UpdatePositionInstance",
                "opcode":669
            }
        ]
    }
}